kaslcred/__init__.py
kaslcred/__main__.py
kaslcred/link.py
kaslcred-0.1.6.dist-info/METADATA
kaslcred-0.1.6.dist-info/WHEEL
kaslcred-0.1.6.dist-info/licenses/LICENSE
kaslcred-0.1.6.dist-info/RECORD
