Metadata-Version: 2.3
Name: kaslcred
Version: 0.1.6
Summary: A credential schema linker for the KERI and ACDC ecosystem.
Project-URL: Homepage, https://github.com/tetraveda/kaslcred
Author-email: Kent Bull <kent@tetraveda.com>
License-File: LICENSE
Classifier: License :: OSI Approved :: Apache Software License
Classifier: Operating System :: OS Independent
Classifier: Programming Language :: Python :: 3
Requires-Python: >=3.12.3
Requires-Dist: keri>=1.1.20
